kotlyn/Download.py
kotlyn/Environ.py
kotlyn/Files.py
kotlyn/Paths.py
kotlyn/__init__.py
kotlyn/__main__.py
kotlyn-0.5.3.dist-info/METADATA
kotlyn-0.5.3.dist-info/WHEEL
kotlyn-0.5.3.dist-info/licenses/LICENSE
kotlyn-0.5.3.dist-info/RECORD
